odoo/addons/sale_coupon_criteria_multi_product/README.rst
odoo/addons/sale_coupon_criteria_multi_product/__init__.py
odoo/addons/sale_coupon_criteria_multi_product/__manifest__.py
odoo/addons/sale_coupon_criteria_multi_product/i18n/it.po
odoo/addons/sale_coupon_criteria_multi_product/i18n/sale_coupon_criteria_multi_product.pot
odoo/addons/sale_coupon_criteria_multi_product/migrations/14.0.1.0.0/pre-migration.py
odoo/addons/sale_coupon_criteria_multi_product/models/__init__.py
odoo/addons/sale_coupon_criteria_multi_product/models/coupon_program.py
odoo/addons/sale_coupon_criteria_multi_product/models/sale_coupon_criteria.py
odoo/addons/sale_coupon_criteria_multi_product/readme/CONFIGURE.rst
odoo/addons/sale_coupon_criteria_multi_product/readme/CONTRIBUTORS.rst
odoo/addons/sale_coupon_criteria_multi_product/readme/DESCRIPTION.rst
odoo/addons/sale_coupon_criteria_multi_product/readme/USAGE.rst
odoo/addons/sale_coupon_criteria_multi_product/security/ir.model.access.csv
odoo/addons/sale_coupon_criteria_multi_product/static/description/icon.png
odoo/addons/sale_coupon_criteria_multi_product/static/description/icon.svg
odoo/addons/sale_coupon_criteria_multi_product/static/description/index.html
odoo/addons/sale_coupon_criteria_multi_product/tests/__init__.py
odoo/addons/sale_coupon_criteria_multi_product/tests/test_sale_coupon_criteria_multi_product.py
odoo/addons/sale_coupon_criteria_multi_product/views/sale_coupon_program_views.xml
odoo14_addon_sale_coupon_criteria_multi_product-14.0.1.0.1.dev4.dist-info/METADATA
odoo14_addon_sale_coupon_criteria_multi_product-14.0.1.0.1.dev4.dist-info/WHEEL
odoo14_addon_sale_coupon_criteria_multi_product-14.0.1.0.1.dev4.dist-info/top_level.txt
odoo14_addon_sale_coupon_criteria_multi_product-14.0.1.0.1.dev4.dist-info/RECORD
